audiorepr/__init__.py
audiorepr/audiolize.py
audiorepr/command.py
audiorepr/data.py
audiorepr/mapper.py
audiorepr/version.py
audiorepr-0.0.2.dist-info/LICENSE
audiorepr-0.0.2.dist-info/METADATA
audiorepr-0.0.2.dist-info/WHEEL
audiorepr-0.0.2.dist-info/entry_points.txt
audiorepr-0.0.2.dist-info/top_level.txt
audiorepr-0.0.2.dist-info/RECORD
