Metadata-Version: 2.1
Name: audiorepr
Version: 0.0.2
Summary: Audiolize your data
Home-page: https://github.com/emptymalei/audiorepr
Author: Lei Ma
Author-email: hi@leima.is
License: MIT
Platform: UNKNOWN
Requires-Dist: midiutil (>=1.2.1)
Requires-Dist: pandas (>=0.23)
Requires-Dist: loguru (>=0.5.3)
Requires-Dist: click (==7.1.2)
Provides-Extra: docs
Requires-Dist: sphinx (>=2.4.1) ; extra == 'docs'
Requires-Dist: sphinx-rtd-theme (>=0.4.3) ; extra == 'docs'
